feeds/__init__.py
feeds/apps.py
feeds/paginator.py
feeds/settings.py
feeds/tasks.py
feeds/urls.py
feeds/migrations/0001_initial.py
feeds/migrations/__init__.py
feeds/static/images/rss.svg
feeds/static/js/bootstrap.min.js.map
feeds/static/js/index.js
feeds/templates/admin/merge_authors.html
feeds/templates/admin/merge_tags.html
feeds/templates/feeds/articles.html
feeds/templates/feeds/author.html
feeds/templates/feeds/authors.html
feeds/templates/feeds/source.html
feeds/templates/feeds/sources.html
feeds/templates/feeds/sources_popular.html
feeds/templates/feeds/tag.html
feeds/templates/feeds/tags.html
feeds/templates/feeds/snippets/pagination.html
feeds/templates/feeds/snippets/tag_author_cloud.html
feeds/templates/feeds/snippets/tag_cloud.html
feeds/templates/feeds/snippets/tag_source_cloud.html
django_rss_feeds-0.0.0.dist-info/LICENSE.txt
django_rss_feeds-0.0.0.dist-info/METADATA
django_rss_feeds-0.0.0.dist-info/WHEEL
django_rss_feeds-0.0.0.dist-info/top_level.txt
django_rss_feeds-0.0.0.dist-info/RECORD
