Metadata-Version: 2.1
Name: django-rss-feeds
Version: 0.0.0
Summary: An aggregator for RSS and Atom feeds.
Home-page: https://github.com/StuartMacKay/django-feeds
Author: Stuart MacKay
Author-email: smackay@flagstonesoftware.com
License: License :: OSI Approved :: Apache Software License
Keywords: django,rss,atom
Classifier: Development Status :: 3 - Alpha
Classifier: Framework :: Django :: 3.2
Classifier: Framework :: Django :: 4.0
Classifier: Intended Audience :: Developers
Classifier: License :: OSI Approved :: Apache Software License
Classifier: Natural Language :: English
Classifier: Programming Language :: Python
Classifier: Programming Language :: Python :: 3
Classifier: Programming Language :: Python :: 3.8
Classifier: Programming Language :: Python :: 3.10
Requires-Python: >=3.8
License-File: LICENSE.txt
Requires-Dist: bs4
Requires-Dist: Django (>=3.2)
Requires-Dist: celery
Requires-Dist: croniter
Requires-Dist: django-daterange-filterspec
Requires-Dist: django-extensions
Requires-Dist: django-tagulous
Requires-Dist: feedparser
Requires-Dist: python-dateutil
Requires-Dist: requests
Requires-Dist: text-unidecode
